SiteLinks/__init__.py
SiteLinks/__main__.py
SiteLinks/urlfetcher.py
SiteLinks-0.0.7.dist-info/METADATA
SiteLinks-0.0.7.dist-info/WHEEL
SiteLinks-0.0.7.dist-info/top_level.txt
SiteLinks-0.0.7.dist-info/RECORD
