Metadata-Version: 2.1
Name: SiteLinks
Version: 0.0.7
Summary: A link-scanning tool to scrape web urls.
Home-page: https://github.com/EllyMandliel/SiteLinks
Author: Elly Mandliel
Author-email: ellykido@google.com
License: UNKNOWN
Platform: UNKNOWN
Classifier: Programming Language :: Python :: 3
Classifier: License :: OSI Approved :: MIT License
Classifier: Operating System :: OS Independent
Requires-Python: >=3
